Metadata-Version: 2.1
Name: dingTalk-notify-to-people
Version: 1.0.1
Summary: 推送Sentry报错信息到钉钉群，并且@具体的人员
Home-page: https://github.com/lanxuexing/sentry-dingtalk-notify
Author: MrChen
Author-email: 1484423781@qq.com
License: MIT
Keywords: sentry dingtalk
Platform: UNKNOWN
Classifier: License :: OSI Approved :: MIT License
Classifier: Programming Language :: Python
Classifier: Programming Language :: Python :: 3
Classifier: Programming Language :: Python :: 3.6
Classifier: Programming Language :: Python :: 3.7
Classifier: Programming Language :: Python :: Implementation :: CPython
Requires-Python: >=3.6.13
License-File: LICENSE
Requires-Dist: sentry (>=21.5.1)
